__init__.py
__main__.py
schemas.py
sniffles2_plot/__init__.py
sniffles2_plot/__main__.py
sniffles2_plot/schemas.py
sniffles2_plot/chart_generator/__init__.py
sniffles2_plot/chart_generator/functions_variables_multi.py
sniffles2_plot/chart_generator/functions_variables_single.py
sniffles2_plot/chart_generator/size_distribution.py
sniffles2_plot/chart_generator/sv_sites_per_genome.py
sniffles2_plot/chart_generator/variant_count.py
sniffles2_plot/cli/__init__.py
sniffles2_plot/cli/arg_parser.py
sniffles2_plot/cli/entry_point.py
sniffles2_plot/cli/generate_charts.py
sniffles2_plot/cli/multi_vcf_visualizer.py
sniffles2_plot/cli/single_vcf_visulaizer.py
sniffles2_plot/helper/__init__.py
sniffles2_plot/helper/io_class.py
sniffles2_plot/parser/__init__.py
sniffles2_plot/parser/vcf_line_parser.py
sniffles2_plot-0.2.1.dist-info/METADATA
sniffles2_plot-0.2.1.dist-info/WHEEL
sniffles2_plot-0.2.1.dist-info/entry_points.txt
sniffles2_plot-0.2.1.dist-info/top_level.txt
sniffles2_plot-0.2.1.dist-info/RECORD
