Metadata-Version: 2.1
Name: sniffles2_plot
Version: 0.2.1
Summary: a visualizer tool for plot generating
Requires-Python: >=3.8
Requires-Dist: seaborn<1,>=0.11.0
Requires-Dist: upsetplot<1,>=0.8.0
Requires-Dist: pandas<2,>=1.1.3
Requires-Dist: matplotlib<4,>=3.3.2
Requires-Dist: numpy<2
